envipyengine/__init__.py
envipyengine/config.py
envipyengine/decorators.py
envipyengine/engine.py
envipyengine/envipymeta.py
envipyengine/error.py
envipyengine/task.py
envipyengine/utils.py
envipyengine/taskengine/__init__.py
envipyengine/taskengine/engine.py
envipyengine/taskengine/task.py
envipyengine/taskengine/taskengine.py
envipyengine-1.0.9.data/scripts/envipyengineconfig.py
envipyengine-1.0.9.dist-info/LICENSE.txt
envipyengine-1.0.9.dist-info/METADATA
envipyengine-1.0.9.dist-info/WHEEL
envipyengine-1.0.9.dist-info/top_level.txt
envipyengine-1.0.9.dist-info/RECORD
